{"controls":{"showBillboardTitle":1,"showCapture":1,"showDollhouse":1,"showFloorplan":1,"showLock":0,"showMap":1,"showPanorama":1,"showRule":0,"showScale":0,"showShare":1,"showTagshare":0,"showTitle":1,"showTour":1,"showVR":1},"createTime":1639974763000,"description":"<p>暂无项目描述</p>","entry":"{\"camera\":{\"quaternion\":[-0.0165,-0.7121,-0.0167,0.7017],\"zoom\":-1},\"mode\":0,\"pano\":\"4\",\"lon\":360.8364473439179,\"lat\":-2.6940086037936015}","filters":0,"floorLogo":"0","floorLogoSize":20,"floorPlanAngle":0.0,"floorPlanCompass":0.0,"floorPlanUser":1,"imgVersion":0,"linkVersion":0,"links":0,"modelKind":"dam","mosaic":0,"mosaicList":[],"music":"02","num":"KJ-tjdiVSFOv8l","sceneFrom":"minion","sceneKind":"tiles","sceneResolution":"4k","surveillances":1,"tags":1,"title":"华发绿洋湾样板间(示例)","tours":1,"version":164,"videos":"{\"data\":[],\"upPath\":\"scene_view_data/KJ-tjdiVSFOv8l/data/Up.txt\",\"version\":3}"}